ciliaseg/__init__.py
ciliaseg/app.py
ciliaseg/eval/__init__.py
ciliaseg/eval/model.py
ciliaseg/eval/polygon.py
ciliaseg/gui/__init__.py
ciliaseg/gui/canvas.py
ciliaseg/state/__init__.py
ciliaseg/state/image.py
ciliaseg/state/stereocilia.py
ciliaseg/train/__init__.py
ciliaseg/utils/__init__.py
ciliaseg/utils/io.py
ciliaseg/widgets/__init__.py
ciliaseg/widgets/control.py
whorl-0.0.0.dev20231121.dist-info/METADATA
whorl-0.0.0.dev20231121.dist-info/WHEEL
whorl-0.0.0.dev20231121.dist-info/entry_points.txt
whorl-0.0.0.dev20231121.dist-info/top_level.txt
whorl-0.0.0.dev20231121.dist-info/RECORD
