Metadata-Version: 2.1
Name: whorl
Version: 0.0.0.dev20231121
Requires-Dist: pyside6 (>=6.4.1)
Requires-Dist: torch (>=2.0.0)
Requires-Dist: torchvision (>=0.14.1)
Requires-Dist: wget (>=3.2)
Requires-Dist: scikit-image (>=0.19.3)
Requires-Dist: numpy (>=1.23.5)
Requires-Dist: tqdm (>=4.64.1)
Requires-Dist: yacs (>=0.1.8)
